README.txt
setup.cfg
setup.py
twodeg/__init__.py
twodeg.nosedjango.egg-info/PKG-INFO
twodeg.nosedjango.egg-info/SOURCES.txt
twodeg.nosedjango.egg-info/dependency_links.txt
twodeg.nosedjango.egg-info/entry_points.txt
twodeg.nosedjango.egg-info/namespace_packages.txt
twodeg.nosedjango.egg-info/requires.txt
twodeg.nosedjango.egg-info/top_level.txt
twodeg.nosedjango.egg-info/zip-safe
twodeg/nosedjango/__init__.py
twodeg/nosedjango/nosedjango.py
twodeg/nosedjango/recipe.py